plot_generator/__init__.py
plot_generator/cli.py
plot_generator/server.py
plot_generator-0.1.5.dist-info/METADATA
plot_generator-0.1.5.dist-info/WHEEL
plot_generator-0.1.5.dist-info/entry_points.txt
plot_generator-0.1.5.dist-info/licenses/LICENSE
plot_generator-0.1.5.dist-info/RECORD
